[{"music":"https://kth-studio.github.io/SaveHaku/Bikini%20Bottom/Bikini%20Bottom/music.mp3",
"image":"https://kth-studio.github.io/SaveHaku/Bikini%20Bottom/imagehd.jpg",
"info":"https://kth-studio.github.io/SaveHaku/Bikini%20Bottom/Bikini%20Bottom/info.json",
"artist":"Save Haku",
"artist_uri":"[{\"info_en\":\"Artist\",\"info_ru\":\"Артист\",\"info_de\":\"Interpret:in\",\"name\":\"Save Haku\",\"image\":\"https://kth-studio.github.io/SaveHaku/image.jpg\",\"link\":\"https://kth-studio.github.io/SaveHaku/link.json\"}]",
"additional":"single",
"album":"Bikini Bottom",
"album_uri":"https://kth-studio.github.io/SaveHaku/Bikini%20Bottom/link.json",
"name":"Bikini Bottom",
"explicit":"no"}]